{
  "ComponentIndexes": {},
  "ControlUniqueIds": {
    "App": 1,
    "Button2": 15,
    "Button2_1": 16,
    "Checkbox1": 11,
    "Checkbox1_1": 31,
    "CompareScreen": 18,
    "DeviceGallery": 6,
    "Galeria de Comparação": 22,
    "galleryTemplate17": 7,
    "galleryTemplate17_1": 23,
    "galleryTemplate18": 13,
    "Group1": 17,
    "Group1_1": 32,
    "HeaderLabel": 4,
    "HeaderLabel_1": 19,
    "Icon1": 20,
    "Image18": 8,
    "Image18_1": 24,
    "Image20": 14,
    "Label2": 5,
    "Label2_1": 21,
    "MainScreen": 3,
    "ManufacturerGallery": 12,
    "Subtitle17": 10,
    "Subtitle17_1": 26,
    "Title17": 9,
    "Title17_1": 25,
    "Title17_2": 27,
    "Title17_3": 28,
    "Title17_4": 29,
    "Title17_5": 30
  },
  "FunctionParamsInvariantScripts": {},
  "FunctionParamsInvariantScriptsOnInstances": {},
  "HeaderLastSavedDateTimeUTC": "07/31/2022 01:35:22",
  "IsLegacyComponentAllowGlobalScopeCase": false,
  "LocalConnectionIDReferences": {},
  "LocalDatabaseReferencesAsEmpty": false,
  "LocalResourceFileNames": {},
  "LocalResourceRootPaths": {},
  "OrderComponentMetadata": {},
  "OrderComponentTemplate": {},
  "OrderDataSource": {
    "Comparelist": 4,
    "CustomGallerySample": 0,
    "Devices": 1,
    "Manufacturers": 2,
    "Produtos": 3
  },
  "OrderGroupControls": {
    "Group1": {
      "HeaderLabel": 1,
      "Label2": 0
    },
    "Group1_1": {
      "HeaderLabel_1": 1,
      "Label2_1": 0
    }
  },
  "OrderPcfTemplate": {},
  "OrderTemplate": {},
  "OrderXMLTemplate": {
    "button": 4,
    "checkbox": 3,
    "gallery": 1,
    "icon": 5,
    "image": 2,
    "label": 0
  },
  "PublishOrderIndices": {
    "App": 0,
    "Button2": 12,
    "Button2_1": 13,
    "Checkbox1": 8,
    "Checkbox1_1": 27,
    "CompareScreen": 0,
    "DeviceGallery": 3,
    "Galeria de Comparação": 18,
    "galleryTemplate17": 4,
    "galleryTemplate17_1": 19,
    "galleryTemplate18": 10,
    "Group1": 1,
    "Group1_1": 17,
    "HeaderLabel": 0,
    "HeaderLabel_1": 14,
    "Icon1": 15,
    "Image18": 5,
    "Image18_1": 20,
    "Image20": 11,
    "Label2": 2,
    "Label2_1": 16,
    "MainScreen": 0,
    "ManufacturerGallery": 9,
    "Subtitle17": 7,
    "Subtitle17_1": 22,
    "Title17": 6,
    "Title17_1": 21,
    "Title17_2": 23,
    "Title17_3": 24,
    "Title17_4": 25,
    "Title17_5": 26
  },
  "ResourcesJsonIndices": {
    "Image-SampleImage": 0
  },
  "RuleScreenIdWithoutScreen": {},
  "TemplateVersions": {},
  "VolatileProperties": {
    "AnalysisLoadTime": 0.259909,
    "ControlCount": {
      "button": 2,
      "checkbox": 2,
      "gallery": 3,
      "galleryTemplate": 3,
      "group": 2,
      "icon": 1,
      "image": 3,
      "label": 12,
      "screen": 2
    },
    "DeserializationLoadTime": 3.0552585,
    "ErrorCount": 0
  },
  "WasLocalDatabaseReferencesEmpty": true
}